WaterQualityAssessor/WaterQualityAssessor.py
WaterQualityAssessor/__init__.py
WaterQualityAssessor-0.1.2.dist-info/LICENSE.txt
WaterQualityAssessor-0.1.2.dist-info/METADATA
WaterQualityAssessor-0.1.2.dist-info/WHEEL
WaterQualityAssessor-0.1.2.dist-info/top_level.txt
WaterQualityAssessor-0.1.2.dist-info/RECORD
