Metadata-Version: 2.1
Name: WaterQualityAssessor
Version: 0.1.2
Summary: Assess the toxicity levels of various contaminants according to EPA MCL standards in post-wildfire habitat watersheds
Home-page: http://pypi.python.org/pypi/WaterQualityAssessor/
Author: Megan Maccagnan
Author-email: meganmaccagnan@mines.edu
License: LICENSE.txt
Platform: UNKNOWN
License-File: LICENSE.txt
Requires-Dist: pandas
Requires-Dist: matplotlib
Requires-Dist: numpy
Requires-Dist: seaborn
Requires-Dist: math
